odoo/addons/mrp_flattened_bom_xlsx_subcontracting_cost/README.rst
odoo/addons/mrp_flattened_bom_xlsx_subcontracting_cost/__init__.py
odoo/addons/mrp_flattened_bom_xlsx_subcontracting_cost/__manifest__.py
odoo/addons/mrp_flattened_bom_xlsx_subcontracting_cost/i18n/it.po
odoo/addons/mrp_flattened_bom_xlsx_subcontracting_cost/i18n/mrp_flattened_bom_xlsx_subcontracting_cost.pot
odoo/addons/mrp_flattened_bom_xlsx_subcontracting_cost/models/__init__.py
odoo/addons/mrp_flattened_bom_xlsx_subcontracting_cost/models/mrp_bom.py
odoo/addons/mrp_flattened_bom_xlsx_subcontracting_cost/readme/CONTRIBUTORS.rst
odoo/addons/mrp_flattened_bom_xlsx_subcontracting_cost/readme/DESCRIPTION.rst
odoo/addons/mrp_flattened_bom_xlsx_subcontracting_cost/readme/USAGE.rst
odoo/addons/mrp_flattened_bom_xlsx_subcontracting_cost/report/__init__.py
odoo/addons/mrp_flattened_bom_xlsx_subcontracting_cost/report/flattened_bom_xlsx.py
odoo/addons/mrp_flattened_bom_xlsx_subcontracting_cost/static/description/icon.png
odoo/addons/mrp_flattened_bom_xlsx_subcontracting_cost/static/description/index.html
odoo14_addon_mrp_flattened_bom_xlsx_subcontracting_cost-14.0.1.0.1.dev5.dist-info/METADATA
odoo14_addon_mrp_flattened_bom_xlsx_subcontracting_cost-14.0.1.0.1.dev5.dist-info/WHEEL
odoo14_addon_mrp_flattened_bom_xlsx_subcontracting_cost-14.0.1.0.1.dev5.dist-info/top_level.txt
odoo14_addon_mrp_flattened_bom_xlsx_subcontracting_cost-14.0.1.0.1.dev5.dist-info/RECORD
